bio_volumentations/__init__.py
bio_volumentations/biovol_typing.py
bio_volumentations/napari_tools.py
bio_volumentations/random_utils.py
bio_volumentations/augmentations/__init__.py
bio_volumentations/augmentations/functional.py
bio_volumentations/augmentations/sitk_utils.py
bio_volumentations/augmentations/transforms.py
bio_volumentations/augmentations/utils.py
bio_volumentations/conversion/__init__.py
bio_volumentations/conversion/functional.py
bio_volumentations/conversion/transforms.py
bio_volumentations/core/__init__.py
bio_volumentations/core/composition.py
bio_volumentations/core/transforms_interface.py
bio_volumentations-1.3.2.dist-info/LICENSE
bio_volumentations-1.3.2.dist-info/METADATA
bio_volumentations-1.3.2.dist-info/WHEEL
bio_volumentations-1.3.2.dist-info/top_level.txt
bio_volumentations-1.3.2.dist-info/RECORD
