Metadata-Version: 2.2
Name: bio-volumentations
Version: 1.3.2
Summary: Library for 3D-5D augmentations of volumetric multi-dimensional time-lapse biomedical images with annotations
Author: Lucia Hradecká, Filip Lux, Samuel Šuľan
Author-email: Lucia Hradecká <lucia.d.hradecka@gmail.com>, Filip Lux <lux.filip@gmail.com>
License: MIT License
Project-URL: Homepage, https://gitlab.fi.muni.cz/cbia/bio-volumentations/-/tree/1.3.2?ref_type=tags
Project-URL: Documentation, https://biovolumentations.readthedocs.io/1.3.2/
Project-URL: Repository, https://gitlab.fi.muni.cz/cbia/bio-volumentations/-/tree/1.3.2?ref_type=tags
Keywords: image,augmentation,3D,volumetric,biomedical,bioimage,preprocessing,transformation
Classifier: Programming Language :: Python :: 3
Classifier: License :: OSI Approved :: MIT License
Classifier: Operating System :: OS Independent
Requires-Python: >=3.1
License-File: LICENSE
Requires-Dist: numpy
Requires-Dist: scipy
Requires-Dist: scikit-image
Requires-Dist: SimpleITK
